mlrl/__init__.py
mlrl/testbed_sklearn/__init__.py
mlrl/testbed_sklearn/batch_config.schema.yml
mlrl/testbed_sklearn/runnables.py
mlrl/testbed_sklearn/experiments/__init__.py
mlrl/testbed_sklearn/experiments/dataset.py
mlrl/testbed_sklearn/experiments/experiment.py
mlrl/testbed_sklearn/experiments/problem_domain.py
mlrl/testbed_sklearn/experiments/input/__init__.py
mlrl/testbed_sklearn/experiments/input/dataset/__init__.py
mlrl/testbed_sklearn/experiments/input/dataset/extension.py
mlrl/testbed_sklearn/experiments/input/dataset/preprocessors/__init__.py
mlrl/testbed_sklearn/experiments/input/dataset/preprocessors/extension.py
mlrl/testbed_sklearn/experiments/input/dataset/preprocessors/one_hot_encoder.py
mlrl/testbed_sklearn/experiments/input/dataset/splitters/__init__.py
mlrl/testbed_sklearn/experiments/input/dataset/splitters/extension.py
mlrl/testbed_sklearn/experiments/input/dataset/splitters/splitter_bipartition.py
mlrl/testbed_sklearn/experiments/input/dataset/splitters/splitter_cross_validation.py
mlrl/testbed_sklearn/experiments/input/sources/__init__.py
mlrl/testbed_sklearn/experiments/input/sources/source_svm.py
mlrl/testbed_sklearn/experiments/output/__init__.py
mlrl/testbed_sklearn/experiments/output/characteristics/__init__.py
mlrl/testbed_sklearn/experiments/output/characteristics/data/__init__.py
mlrl/testbed_sklearn/experiments/output/characteristics/data/characteristics.py
mlrl/testbed_sklearn/experiments/output/characteristics/data/characteristics_data.py
mlrl/testbed_sklearn/experiments/output/characteristics/data/characteristics_prediction.py
mlrl/testbed_sklearn/experiments/output/characteristics/data/extension.py
mlrl/testbed_sklearn/experiments/output/characteristics/data/extension_prediction.py
mlrl/testbed_sklearn/experiments/output/characteristics/data/matrix_feature.py
mlrl/testbed_sklearn/experiments/output/characteristics/data/matrix_label.py
mlrl/testbed_sklearn/experiments/output/characteristics/data/matrix_output.py
mlrl_testbed_sklearn-0.15.1.dist-info/METADATA
mlrl_testbed_sklearn-0.15.1.dist-info/WHEEL
mlrl_testbed_sklearn-0.15.1.dist-info/top_level.txt
mlrl_testbed_sklearn-0.15.1.dist-info/RECORD
